{"doc":" 知识库角色与知识库关联Service业务层处理\n\n @author ageerle\n @date 2025-07-19\n","fields":[],"enumConstants":[],"methods":[{"name":"queryById","paramTypes":["java.lang.Long"],"doc":" 查询知识库角色与知识库关联\n"},{"name":"queryPageList","paramTypes":["org.ruoyi.domain.bo.KnowledgeRoleRelationBo","org.ruoyi.core.page.PageQuery"],"doc":" 查询知识库角色与知识库关联列表\n"},{"name":"queryList","paramTypes":["org.ruoyi.domain.bo.KnowledgeRoleRelationBo"],"doc":" 查询知识库角色与知识库关联列表\n"},{"name":"insertByBo","paramTypes":["org.ruoyi.domain.bo.KnowledgeRoleRelationBo"],"doc":" 新增知识库角色与知识库关联\n"},{"name":"updateByBo","paramTypes":["org.ruoyi.domain.bo.KnowledgeRoleRelationBo"],"doc":" 修改知识库角色与知识库关联\n"},{"name":"validEntityBeforeSave","paramTypes":["org.ruoyi.domain.KnowledgeRoleRelation"],"doc":" 保存前的数据校验\n"},{"name":"deleteWithValidByIds","paramTypes":["java.util.Collection","java.lang.Boolean"],"doc":" 批量删除知识库角色与知识库关联\n"}],"constructors":[]}